pycryptor/__init__.py
pycryptor/__main__.py
pycryptor/app.py
pycryptor/file_io.py
pycryptor/signature.py
pycryptor/utils.py
PyCryptor-0.1.3.dist-info/LICENSE
PyCryptor-0.1.3.dist-info/METADATA
PyCryptor-0.1.3.dist-info/WHEEL
PyCryptor-0.1.3.dist-info/entry_points.txt
PyCryptor-0.1.3.dist-info/top_level.txt
PyCryptor-0.1.3.dist-info/RECORD
