Metadata-Version: 2.1
Name: PyCryptor
Version: 0.1.3
Summary: cli tool for encrypting and decrypting files
Home-page: https://github.com/Serphyus/PyCryptor
Author: Serphy
Author-email: serphyus@gmail.com
License: MIT
Keywords: cryptography,cli,file-encryption
Platform: Linux
Platform: Mac OSX
Platform: Windows
Classifier: Development Status :: 4 - Beta
Classifier: Intended Audience :: Developers
Classifier: License :: OSI Approved :: MIT License
Classifier: Environment :: Console
Classifier: Operating System :: OS Independent
Classifier: Programming Language :: Python :: 3
Classifier: Natural Language :: English
Requires-Python: >=3.7
License-File: LICENSE
Requires-Dist: pycryptodome
Requires-Dist: rich
